<?xml version="1.0" encoding="utf-8"?>
<FamilyInfo xmlns:xsd="http://www.w3.org/2001/XMLSchema" xmlns:xsi="http://www.w3.org/2001/XMLSchema-instance">
  <RevitVersion>2019</RevitVersion>
  <CategoryId>-2001140</CategoryId>
  <FamTHash>8PFpRaRxm_QefZy_y459Kw!1YT87ksFjQjDYHTzlMakuw</FamTHash>
  <LocalPath>C:\PROGRAMDATA\KINSHIP\ANDEKAN.COM\CACHE\5923K\5923243\HEAT PUMP-HORIZONTAL-ELEC HEATED-CARRIER-PACKAGED-0.5-6 TONS.RFA</LocalPath>
  <Host>Non hosted</Host>
  <PlacementType>OneLevelBased</PlacementType>
  <Category>Mechanical Equipment</Category>
  <DisplayUnitSystem>METRIC</DisplayUnitSystem>
  <Properties>
    <Parameter Id="-1153100" Numeric="0">None</Parameter>
    <Parameter Id="-1002067" />
    <Parameter Id="-1012833" Numeric="0">No</Parameter>
    <Parameter Id="-1012808" Numeric="1">Yes</Parameter>
    <Parameter Id="-1012811" Numeric="0">No</Parameter>
    <Parameter Id="-1114206" Numeric="0">Normal</Parameter>
    <Parameter Id="-1152375" Numeric="0">Use Radius</Parameter>
    <Parameter Id="-1012834" Numeric="0">No</Parameter>
    <Parameter Id="-1002502">23.75.10.21.17</Parameter>
    <Parameter Id="-1002503">Water-Source Heat Pumps</Parameter>
    <Parameter Id="-1114399" Numeric="0">No</Parameter>
    <Parameter Id="-1012843">0</Parameter>
  </Properties>
  <Types>
    <FamilyType Name="50PSH-007">
      <Parameters>
        <Parameter Id="84059">208 V</Parameter>
        <Parameter Id="84060">0.8</Parameter>
        <Parameter Id="84061">1</Parameter>
        <Parameter Id="84062">HVAC</Parameter>
        <Parameter Id="84063">0 VA</Parameter>
        <Parameter Id="84064">7000 Btu/h</Parameter>
        <Parameter Id="84066">8800 Btu/h</Parameter>
        <Parameter Id="84065">6800 Btu/h</Parameter>
        <Parameter Id="83991">1</Parameter>
        <Parameter Id="84244">1</Parameter>
        <Parameter Id="84052">0</Parameter>
        <Parameter Id="84053">6</Parameter>
        <Parameter Id="84054">6</Parameter>
        <Parameter Id="84055">6</Parameter>
        <Parameter Id="84056">36</Parameter>
        <Parameter Id="84057">6</Parameter>
        <Parameter Id="84716">1</Parameter>
        <Parameter Id="84069">0 CFM</Parameter>
        <Parameter Id="84070">0 CFM</Parameter>
        <Parameter Id="84068">0 in-wg</Parameter>
        <Parameter Id="84874">Effect - Carrier - Black</Parameter>
        <Parameter Id="84873">Metal - Carrier - Brass</Parameter>
        <Parameter Id="84037">Metal - Carrier - Steel Galvanized</Parameter>
        <Parameter Id="84036">Metal - Carrier - Finned</Parameter>
        <Parameter Id="84058">Clearance Zone</Parameter>
        <Parameter Id="84035">Metal - Carrier - White Paint Finish</Parameter>
        <Parameter Id="83895">21.75</Parameter>
        <Parameter Id="83896">43.25</Parameter>
        <Parameter Id="83897">16.75</Parameter>
        <Parameter Id="-1010104">www.carrier.com</Parameter>
        <Parameter Id="84184">0</Parameter>
        <Parameter Id="-1010109">50PSH</Parameter>
        <Parameter Id="-1010108">Carrier Corporation</Parameter>
        <Parameter Id="84067">15.7</Parameter>
        <Parameter Id="-1002500">D3050200</Parameter>
        <Parameter Id="-1152384">&lt;By Category&gt;</Parameter>
        <Parameter Id="-1140422" />
        <Parameter Id="-1010105" />
        <Parameter Id="-1010103" />
        <Parameter Id="-1001205" />
        <Parameter Id="83973">3/8"</Parameter>
        <Parameter Id="83977">13.87</Parameter>
        <Parameter Id="83978">2.25</Parameter>
        <Parameter Id="83989">0.572</Parameter>
        <Parameter Id="83972">3/4"</Parameter>
        <Parameter Id="84616">0.5</Parameter>
        <Parameter Id="84245">0</Parameter>
        <Parameter Id="84247">4.62</Parameter>
        <Parameter Id="84248">4.62</Parameter>
        <Parameter Id="84332">8.495</Parameter>
        <Parameter Id="84246">3.5</Parameter>
        <Parameter Id="84319">12.375</Parameter>
        <Parameter Id="83998">1</Parameter>
        <Parameter Id="83995">3.5</Parameter>
        <Parameter Id="83993">11 3/4"</Parameter>
        <Parameter Id="83994">7 3/4"</Parameter>
        <Parameter Id="83992">0</Parameter>
        <Parameter Id="84706">0.5</Parameter>
        <Parameter Id="84016">20 1/4"</Parameter>
        <Parameter Id="84017">13"</Parameter>
        <Parameter Id="84014">21.25</Parameter>
        <Parameter Id="84015">15</Parameter>
        <Parameter Id="83908">0</Parameter>
        <Parameter Id="84728">0.375</Parameter>
        <Parameter Id="84527">38.125</Parameter>
        <Parameter Id="84477">60.875</Parameter>
        <Parameter Id="84476">25.25</Parameter>
        <Parameter Id="84440">0</Parameter>
        <Parameter Id="84409">0</Parameter>
        <Parameter Id="84353">-0.125</Parameter>
        <Parameter Id="84352">21.125</Parameter>
        <Parameter Id="84349">-3.875</Parameter>
        <Parameter Id="84348">3.875</Parameter>
        <Parameter Id="84329">1</Parameter>
        <Parameter Id="84030">1.375</Parameter>
        <Parameter Id="84020">1.35</Parameter>
        <Parameter Id="84019">-0.125</Parameter>
        <Parameter Id="84018">21.125</Parameter>
        <Parameter Id="84013">-19.625</Parameter>
        <Parameter Id="84655">2</Parameter>
        <Parameter Id="84652">-1.125</Parameter>
        <Parameter Id="84261">21.55</Parameter>
        <Parameter Id="84012">19.625</Parameter>
        <Parameter Id="84258">2</Parameter>
        <Parameter Id="84243">-19.625</Parameter>
        <Parameter Id="84242">0.5</Parameter>
        <Parameter Id="84208">1</Parameter>
        <Parameter Id="84170">21.75</Parameter>
        <Parameter Id="84623">17.462</Parameter>
        <Parameter Id="84622">2</Parameter>
        <Parameter Id="84621">2.288</Parameter>
        <Parameter Id="84597">40.125</Parameter>
        <Parameter Id="84005">10.875</Parameter>
        <Parameter Id="84596">59.731</Parameter>
        <Parameter Id="84127">1.1</Parameter>
        <Parameter Id="84126">0</Parameter>
        <Parameter Id="84051">0.375</Parameter>
        <Parameter Id="84050">20.625</Parameter>
        <Parameter Id="84047">2.375</Parameter>
        <Parameter Id="84034">-0.125</Parameter>
        <Parameter Id="84033">21.125</Parameter>
        <Parameter Id="84607">1</Parameter>
        <Parameter Id="83974">0.5</Parameter>
        <Parameter Id="84274">4.75</Parameter>
        <Parameter Id="84273">2.25</Parameter>
        <Parameter Id="83986">3/8"</Parameter>
        <Parameter Id="83979">1</Parameter>
        <Parameter Id="83990">0.572</Parameter>
        <Parameter Id="83985">3/4"</Parameter>
        <Parameter Id="84753">0</Parameter>
        <Parameter Id="84294">0.75</Parameter>
        <Parameter Id="84327">90°</Parameter>
        <Parameter Id="84254">180°</Parameter>
        <Parameter Id="84004">0°</Parameter>
      </Parameters>
    </FamilyType>
  </Types>
  <Parameters>
    <ParameterInfo Name="Air Pressure Drop" Id="84068">
      <Group>PG_MECHANICAL</Group>
      <Type>HVACPressure</Type>
      <Storage>Double</Storage>
      <Unit>Inches of water (60 °F)</Unit>
      <Instance>true</Instance>
      <CanAssignFormula>true</CanAssignFormula>
    </ParameterInfo>
    <ParameterInfo Name="Always vertical" Id="-1012808">
      <BuiltinID>FAMILY_ALWAYS_VERTICAL</BuiltinID>
      <Type>YesNo</Type>
      <Storage>Integer</Storage>
    </ParameterInfo>
    <ParameterInfo Name="Angle 1" Id="84004">
      <Type>Angle</Type>
      <Storage>Double</Storage>
      <Unit>Decimal degrees</Unit>
      <Instance>true</Instance>
      <FormulaDetermined>true</FormulaDetermined>
      <CanAssignFormula>true</CanAssignFormula>
      <Formula>if(Left RA, 0°, 180°)</Formula>
    </ParameterInfo>
    <ParameterInfo Name="Angle 2" Id="84254">
      <Type>Angle</Type>
      <Storage>Double</Storage>
      <Unit>Decimal degrees</Unit>
      <Instance>true</Instance>
      <FormulaDetermined>true</FormulaDetermined>
      <CanAssignFormula>true</CanAssignFormula>
      <Formula>if(Straight Through, 0°, 180°)</Formula>
    </ParameterInfo>
    <ParameterInfo Name="Angle 3" Id="84327">
      <Type>Angle</Type>
      <Storage>Double</Storage>
      <Unit>Decimal degrees</Unit>
      <Instance>true</Instance>
      <FormulaDetermined>true</FormulaDetermined>
      <CanAssignFormula>true</CanAssignFormula>
      <Formula>if(and(Straight Through, Left RA), 0°, if(and(Straight Through, Right RA), 180°, 90°))</Formula>
    </ParameterInfo>
    <ParameterInfo Name="Apparent Load" Id="84063">
      <Group>PG_AELECTRICAL</Group>
      <Type>ElectricalApparentPower</Type>
      <Storage>Double</Storage>
      <Unit>Volt-amperes</Unit>
      <Instance>true</Instance>
      <CanAssignFormula>true</CanAssignFormula>
    </ParameterInfo>
    <ParameterInfo Name="Assembly Code" Id="-1002500">
      <BuiltinID>UNIFORMAT_CODE</BuiltinID>
      <Group>PG_IDENTITY_DATA</Group>
      <Type>Text</Type>
      <Storage>String</Storage>
    </ParameterInfo>
    <ParameterInfo Name="Base Height" Id="84294">
      <Type>Length</Type>
      <Storage>Double</Storage>
      <Unit>Decimal inches</Unit>
      <CanAssignFormula>true</CanAssignFormula>
    </ParameterInfo>
    <ParameterInfo Name="Base Rail" Id="84716">
      <Group>PG_CONSTRAINTS</Group>
      <Type>YesNo</Type>
      <Storage>Integer</Storage>
      <Instance>true</Instance>
      <CanAssignFormula>true</CanAssignFormula>
    </ParameterInfo>
    <ParameterInfo Name="Base Rail Visibility" Id="84753">
      <Type>YesNo</Type>
      <Storage>Integer</Storage>
      <Instance>true</Instance>
      <FormulaDetermined>true</FormulaDetermined>
      <CanAssignFormula>true</CanAssignFormula>
      <Formula>and(Base Rail, Tonnage &gt; 2.4)</Formula>
    </ParameterInfo>
    <ParameterInfo Name="Body Material" Id="84035">
      <Group>PG_MATERIALS</Group>
      <Type>Material</Type>
      <Storage>ElementId</Storage>
    </ParameterInfo>
    <ParameterInfo Name="Classification" Id="-1153100">
      <BuiltinID>MEP_EQUIPMENT_CLASSIFICATION</BuiltinID>
      <Group>PG_MECHANICAL</Group>
      <Storage>Integer</Storage>
    </ParameterInfo>
    <ParameterInfo Name="Clearance Back" Id="84057">
      <Group>PG_CONSTRAINTS</Group>
      <Type>Length</Type>
      <Storage>Double</Storage>
      <Unit>Decimal inches</Unit>
      <Instance>true</Instance>
      <CanAssignFormula>true</CanAssignFormula>
    </ParameterInfo>
    <ParameterInfo Name="Clearance Front" Id="84056">
      <Group>PG_CONSTRAINTS</Group>
      <Type>Length</Type>
      <Storage>Double</Storage>
      <Unit>Decimal inches</Unit>
      <Instance>true</Instance>
      <CanAssignFormula>true</CanAssignFormula>
    </ParameterInfo>
    <ParameterInfo Name="Clearance Left" Id="84055">
      <Group>PG_CONSTRAINTS</Group>
      <Type>Length</Type>
      <Storage>Double</Storage>
      <Unit>Decimal inches</Unit>
      <Instance>true</Instance>
      <CanAssignFormula>true</CanAssignFormula>
    </ParameterInfo>
    <ParameterInfo Name="Clearance Material" Id="84058">
      <Group>PG_MATERIALS</Group>
      <Type>Material</Type>
      <Storage>ElementId</Storage>
    </ParameterInfo>
    <ParameterInfo Name="Clearance Right" Id="84054">
      <Group>PG_CONSTRAINTS</Group>
      <Type>Length</Type>
      <Storage>Double</Storage>
      <Unit>Decimal inches</Unit>
      <Instance>true</Instance>
      <CanAssignFormula>true</CanAssignFormula>
    </ParameterInfo>
    <ParameterInfo Name="Clearance Top" Id="84053">
      <Group>PG_CONSTRAINTS</Group>
      <Type>Length</Type>
      <Storage>Double</Storage>
      <Unit>Decimal inches</Unit>
      <Instance>true</Instance>
      <CanAssignFormula>true</CanAssignFormula>
    </ParameterInfo>
    <ParameterInfo Name="Clearance Zones" Id="84052">
      <Group>PG_CONSTRAINTS</Group>
      <Type>YesNo</Type>
      <Storage>Integer</Storage>
      <Instance>true</Instance>
      <CanAssignFormula>true</CanAssignFormula>
    </ParameterInfo>
    <ParameterInfo Name="Cooling Capacity" Id="84065">
      <Group>PG_ENERGY_ANALYSIS</Group>
      <Type>HVACCoolingLoad</Type>
      <Storage>Double</Storage>
      <Unit>BTU (British Thermal Units) per hour</Unit>
      <CanAssignFormula>true</CanAssignFormula>
    </ParameterInfo>
    <ParameterInfo Name="Cost" Id="-1001205">
      <BuiltinID>DOOR_COST</BuiltinID>
      <Group>PG_IDENTITY_DATA</Group>
      <Type>Currency</Type>
      <Storage>Double</Storage>
      <Unit>Currency</Unit>
      <CanAssignFormula>true</CanAssignFormula>
    </ParameterInfo>
    <ParameterInfo Name="Cut with Voids When Loaded" Id="-1012811">
      <BuiltinID>FAMILY_ALLOW_CUT_WITH_VOIDS</BuiltinID>
      <Type>YesNo</Type>
      <Storage>Integer</Storage>
    </ParameterInfo>
    <ParameterInfo Name="Description" Id="-1010103">
      <BuiltinID>ALL_MODEL_DESCRIPTION</BuiltinID>
      <Group>PG_IDENTITY_DATA</Group>
      <Type>Text</Type>
      <Storage>String</Storage>
      <CanAssignFormula>true</CanAssignFormula>
    </ParameterInfo>
    <ParameterInfo Name="Drain Diameter" Id="83985">
      <Type>PipeSize</Type>
      <Storage>Double</Storage>
      <Unit>Fractional inches</Unit>
      <CanAssignFormula>true</CanAssignFormula>
      <Formula>Drain Radius * 2</Formula>
    </ParameterInfo>
    <ParameterInfo Name="Drain Hole Radius" Id="83990">
      <Type>Length</Type>
      <Storage>Double</Storage>
      <Unit>Decimal inches</Unit>
      <CanAssignFormula>true</CanAssignFormula>
      <Formula>Drain Radius + 0.197"</Formula>
    </ParameterInfo>
    <ParameterInfo Name="Drain Offset" Id="83979">
      <Type>Length</Type>
      <Storage>Double</Storage>
      <Unit>Decimal inches</Unit>
      <CanAssignFormula>true</CanAssignFormula>
    </ParameterInfo>
    <ParameterInfo Name="Drain Radius" Id="83986">
      <Type>PipeSize</Type>
      <Storage>Double</Storage>
      <Unit>Fractional inches</Unit>
      <CanAssignFormula>true</CanAssignFormula>
    </ParameterInfo>
    <ParameterInfo Name="Edited by" Id="-1002067">
      <BuiltinID>EDITED_BY</BuiltinID>
      <Group>PG_IDENTITY_DATA</Group>
      <Type>Text</Type>
      <Storage>String</Storage>
      <ReadOnly>true</ReadOnly>
    </ParameterInfo>
    <ParameterInfo Name="EER" Id="84067">
      <Group>PG_IDENTITY_DATA</Group>
      <Type>Number</Type>
      <Storage>Double</Storage>
      <Unit>General</Unit>
      <CanAssignFormula>true</CanAssignFormula>
    </ParameterInfo>
    <ParameterInfo Name="End Blow" Id="84244">
      <Group>PG_CONSTRAINTS</Group>
      <Type>YesNo</Type>
      <Storage>Integer</Storage>
      <Instance>true</Instance>
      <CanAssignFormula>true</CanAssignFormula>
    </ParameterInfo>
    <ParameterInfo Name="Heating Capacity" Id="84066">
      <Group>PG_ENERGY_ANALYSIS</Group>
      <Type>HVACHeatingLoad</Type>
      <Storage>Double</Storage>
      <Unit>BTU (British Thermal Units) per hour</Unit>
      <CanAssignFormula>true</CanAssignFormula>
    </ParameterInfo>
    <ParameterInfo Name="Height" Id="83897">
      <Group>PG_GEOMETRY</Group>
      <Type>Length</Type>
      <Storage>Double</Storage>
      <Unit>Decimal inches</Unit>
      <CanAssignFormula>true</CanAssignFormula>
    </ParameterInfo>
    <ParameterInfo Name="Highlight Material 1" Id="84036">
      <Group>PG_MATERIALS</Group>
      <Type>Material</Type>
      <Storage>ElementId</Storage>
    </ParameterInfo>
    <ParameterInfo Name="Highlight Material 2" Id="84037">
      <Group>PG_MATERIALS</Group>
      <Type>Material</Type>
      <Storage>ElementId</Storage>
    </ParameterInfo>
    <ParameterInfo Name="Highlight Material 3" Id="84873">
      <Group>PG_MATERIALS</Group>
      <Type>Material</Type>
      <Storage>ElementId</Storage>
    </ParameterInfo>
    <ParameterInfo Name="Highlight Material 4" Id="84874">
      <Group>PG_MATERIALS</Group>
      <Type>Material</Type>
      <Storage>ElementId</Storage>
    </ParameterInfo>
    <ParameterInfo Name="Host" Id="-1012843">
      <BuiltinID>FAMILY_HOSTING_BEHAVIOR</BuiltinID>
      <Group>PG_CONSTRAINTS</Group>
      <Storage>Integer</Storage>
      <ReadOnly>true</ReadOnly>
    </ParameterInfo>
    <ParameterInfo Name="Keynote" Id="-1140422">
      <BuiltinID>KEYNOTE_PARAM</BuiltinID>
      <Group>PG_IDENTITY_DATA</Group>
      <Type>Text</Type>
      <Storage>String</Storage>
      <CanAssignFormula>true</CanAssignFormula>
    </ParameterInfo>
    <ParameterInfo Name="Knockout 1 Offset" Id="84273">
      <Type>Length</Type>
      <Storage>Double</Storage>
      <Unit>Decimal inches</Unit>
      <CanAssignFormula>true</CanAssignFormula>
    </ParameterInfo>
    <ParameterInfo Name="Knockout 2 Offset" Id="84274">
      <Type>Length</Type>
      <Storage>Double</Storage>
      <Unit>Decimal inches</Unit>
      <CanAssignFormula>true</CanAssignFormula>
    </ParameterInfo>
    <ParameterInfo Name="Knockout Radius" Id="83974">
      <Type>Length</Type>
      <Storage>Double</Storage>
      <Unit>Decimal inches</Unit>
      <CanAssignFormula>true</CanAssignFormula>
    </ParameterInfo>
    <ParameterInfo Name="Left RA" Id="83991">
      <Group>PG_CONSTRAINTS</Group>
      <Type>YesNo</Type>
      <Storage>Integer</Storage>
      <Instance>true</Instance>
      <CanAssignFormula>true</CanAssignFormula>
    </ParameterInfo>
    <ParameterInfo Name="Length" Id="83896">
      <Group>PG_GEOMETRY</Group>
      <Type>Length</Type>
      <Storage>Double</Storage>
      <Unit>Decimal inches</Unit>
      <CanAssignFormula>true</CanAssignFormula>
    </ParameterInfo>
    <ParameterInfo Name="Length 1" Id="84607">
      <Type>Length</Type>
      <Storage>Double</Storage>
      <Unit>Decimal inches</Unit>
      <CanAssignFormula>true</CanAssignFormula>
      <Formula>Knockout Radius + 0.5"</Formula>
    </ParameterInfo>
    <ParameterInfo Name="Length 10" Id="84033">
      <Type>Length</Type>
      <Storage>Double</Storage>
      <Unit>Decimal inches</Unit>
      <FormulaDetermined>true</FormulaDetermined>
      <CanAssignFormula>true</CanAssignFormula>
      <Formula>Length / 2 - RA Y Offset ST</Formula>
    </ParameterInfo>
    <ParameterInfo Name="Length 11" Id="84034">
      <Type>Length</Type>
      <Storage>Double</Storage>
      <Unit>Decimal inches</Unit>
      <FormulaDetermined>true</FormulaDetermined>
      <CanAssignFormula>true</CanAssignFormula>
      <Formula>0" - (RA Filter Width - Length 10)</Formula>
    </ParameterInfo>
    <ParameterInfo Name="Length 12" Id="84047">
      <Type>Length</Type>
      <Storage>Double</Storage>
      <Unit>Decimal inches</Unit>
      <FormulaDetermined>true</FormulaDetermined>
      <CanAssignFormula>true</CanAssignFormula>
      <Formula>Length 9 + ((RA Filter Height - RA Height) / 2)</Formula>
    </ParameterInfo>
    <ParameterInfo Name="Length 13" Id="84349">
      <Type>Length</Type>
      <Storage>Double</Storage>
      <Unit>Decimal inches</Unit>
      <CanAssignFormula>true</CanAssignFormula>
      <Formula>0" - Length 16</Formula>
    </ParameterInfo>
    <ParameterInfo Name="Length 14" Id="84050">
      <Type>Length</Type>
      <Storage>Double</Storage>
      <Unit>Decimal inches</Unit>
      <Instance>true</Instance>
      <FormulaDetermined>true</FormulaDetermined>
      <CanAssignFormula>true</CanAssignFormula>
      <Formula>if(Right RA, Length 35 - ((RA Filter Width - RA Width) / 2), Length 34 - ((RA Filter Width - RA Width) / 2))</Formula>
    </ParameterInfo>
    <ParameterInfo Name="Length 15" Id="84051">
      <Type>Length</Type>
      <Storage>Double</Storage>
      <Unit>Decimal inches</Unit>
      <Instance>true</Instance>
      <FormulaDetermined>true</FormulaDetermined>
      <CanAssignFormula>true</CanAssignFormula>
      <Formula>0" - (RA Width - Length 14)</Formula>
    </ParameterInfo>
    <ParameterInfo Name="Length 16" Id="84348">
      <Type>Length</Type>
      <Storage>Double</Storage>
      <Unit>Decimal inches</Unit>
      <CanAssignFormula>true</CanAssignFormula>
      <Formula>SA Height / 2</Formula>
    </ParameterInfo>
    <ParameterInfo Name="Length 17" Id="84126">
      <Type>Length</Type>
      <Storage>Double</Storage>
      <Unit>Decimal inches</Unit>
      <Instance>true</Instance>
      <FormulaDetermined>true</FormulaDetermined>
      <CanAssignFormula>true</CanAssignFormula>
      <Formula>if(Left RA, 0", 1.1")</Formula>
    </ParameterInfo>
    <ParameterInfo Name="Length 18" Id="84127">
      <Type>Length</Type>
      <Storage>Double</Storage>
      <Unit>Decimal inches</Unit>
      <Instance>true</Instance>
      <FormulaDetermined>true</FormulaDetermined>
      <CanAssignFormula>true</CanAssignFormula>
      <Formula>if(Left RA, 1.1", 0")</Formula>
    </ParameterInfo>
    <ParameterInfo Name="Length 19" Id="84596">
      <Type>Length</Type>
      <Storage>Double</Storage>
      <Unit>Decimal inches</Unit>
      <Instance>true</Instance>
      <FormulaDetermined>true</FormulaDetermined>
      <CanAssignFormula>true</CanAssignFormula>
      <Formula>50" + Width / 2 - Water Hole Radius * 2</Formula>
    </ParameterInfo>
    <ParameterInfo Name="Length 2" Id="84005">
      <Type>Length</Type>
      <Storage>Double</Storage>
      <Unit>Decimal inches</Unit>
      <CanAssignFormula>true</CanAssignFormula>
      <Formula>Width / 2</Formula>
    </ParameterInfo>
    <ParameterInfo Name="Length 20" Id="84597">
      <Type>Length</Type>
      <Storage>Double</Storage>
      <Unit>Decimal inches</Unit>
      <Instance>true</Instance>
      <FormulaDetermined>true</FormulaDetermined>
      <CanAssignFormula>true</CanAssignFormula>
      <Formula>50" - Width / 2 + Length 1</Formula>
    </ParameterInfo>
    <ParameterInfo Name="Length 21" Id="84621">
      <Type>Length</Type>
      <Storage>Double</Storage>
      <Unit>Decimal inches</Unit>
      <Instance>true</Instance>
      <CanAssignFormula>true</CanAssignFormula>
      <Formula>Water Hole Radius * 4</Formula>
    </ParameterInfo>
    <ParameterInfo Name="Length 22" Id="84622">
      <Type>Length</Type>
      <Storage>Double</Storage>
      <Unit>Decimal inches</Unit>
      <Instance>true</Instance>
      <CanAssignFormula>true</CanAssignFormula>
      <Formula>Length 1 * 2</Formula>
    </ParameterInfo>
    <ParameterInfo Name="Length 23" Id="84623">
      <Type>Length</Type>
      <Storage>Double</Storage>
      <Unit>Decimal inches</Unit>
      <Instance>true</Instance>
      <FormulaDetermined>true</FormulaDetermined>
      <CanAssignFormula>true</CanAssignFormula>
      <Formula>if(Left RA, Width - Water Hole Radius * 4 - Length 33, Water Hole Radius * 4 + Length 33)</Formula>
    </ParameterInfo>
    <ParameterInfo Name="Length 24" Id="84170">
      <Type>Length</Type>
      <Storage>Double</Storage>
      <Unit>Decimal inches</Unit>
      <Instance>true</Instance>
      <FormulaDetermined>true</FormulaDetermined>
      <CanAssignFormula>true</CanAssignFormula>
      <Formula>if(Left RA, Width, 0")</Formula>
    </ParameterInfo>
    <ParameterInfo Name="Length 25" Id="84208">
      <Type>Length</Type>
      <Storage>Double</Storage>
      <Unit>Decimal inches</Unit>
      <Instance>true</Instance>
      <FormulaDetermined>true</FormulaDetermined>
      <CanAssignFormula>true</CanAssignFormula>
      <Formula>if(Clearance Zones, 0", 1")</Formula>
    </ParameterInfo>
    <ParameterInfo Name="Length 26" Id="84242">
      <Type>Length</Type>
      <Storage>Double</Storage>
      <Unit>Decimal inches</Unit>
      <Instance>true</Instance>
      <FormulaDetermined>true</FormulaDetermined>
      <CanAssignFormula>true</CanAssignFormula>
      <Formula>if(Left RA, RA Y Offset ST, Length 33)</Formula>
    </ParameterInfo>
    <ParameterInfo Name="Length 27" Id="84243">
      <Type>Length</Type>
      <Storage>Double</Storage>
      <Unit>Decimal inches</Unit>
      <Instance>true</Instance>
      <FormulaDetermined>true</FormulaDetermined>
      <CanAssignFormula>true</CanAssignFormula>
      <Formula>0" - ((Length / 2) - Length 33)</Formula>
    </ParameterInfo>
    <ParameterInfo Name="Length 28" Id="84440">
      <Type>Length</Type>
      <Storage>Double</Storage>
      <Unit>Decimal inches</Unit>
      <Instance>true</Instance>
      <FormulaDetermined>true</FormulaDetermined>
      <CanAssignFormula>true</CanAssignFormula>
      <Formula>if(End Blow, 0", Width)</Formula>
    </ParameterInfo>
    <ParameterInfo Name="Length 29" Id="84258">
      <Type>Length</Type>
      <Storage>Double</Storage>
      <Unit>Decimal inches</Unit>
      <Instance>true</Instance>
      <FormulaDetermined>true</FormulaDetermined>
      <CanAssignFormula>true</CanAssignFormula>
      <Formula>if(Left RA, Length 33, RA Y Offset ST)</Formula>
    </ParameterInfo>
    <ParameterInfo Name="Length 3" Id="84012">
      <Type>Length</Type>
      <Storage>Double</Storage>
      <Unit>Decimal inches</Unit>
      <FormulaDetermined>true</FormulaDetermined>
      <CanAssignFormula>true</CanAssignFormula>
      <Formula>(Length / 2) - Length 33</Formula>
    </ParameterInfo>
    <ParameterInfo Name="Length 30" Id="84261">
      <Type>Length</Type>
      <Storage>Double</Storage>
      <Unit>Decimal inches</Unit>
      <CanAssignFormula>true</CanAssignFormula>
      <Formula>Width - 0.2"</Formula>
    </ParameterInfo>
    <ParameterInfo Name="Length 31" Id="84409">
      <Type>Length</Type>
      <Storage>Double</Storage>
      <Unit>Decimal inches</Unit>
      <Instance>true</Instance>
      <FormulaDetermined>true</FormulaDetermined>
      <CanAssignFormula>true</CanAssignFormula>
      <Formula>if(Left RA, 0", Width)</Formula>
    </ParameterInfo>
    <ParameterInfo Name="Length 32" Id="84652">
      <Type>Length</Type>
      <Storage>Double</Storage>
      <Unit>Decimal inches</Unit>
      <Instance>true</Instance>
      <FormulaDetermined>true</FormulaDetermined>
      <CanAssignFormula>true</CanAssignFormula>
      <Formula>if(Left RA, Length 35 - 1", Length 35)</Formula>
    </ParameterInfo>
    <ParameterInfo Name="Length 33" Id="84655">
      <Type>Length</Type>
      <Storage>Double</Storage>
      <Unit>Decimal inches</Unit>
      <FormulaDetermined>true</FormulaDetermined>
      <CanAssignFormula>true</CanAssignFormula>
      <Formula>2"</Formula>
    </ParameterInfo>
    <ParameterInfo Name="Length 34" Id="84352">
      <Type>Length</Type>
      <Storage>Double</Storage>
      <Unit>Decimal inches</Unit>
      <Instance>true</Instance>
      <FormulaDetermined>true</FormulaDetermined>
      <CanAssignFormula>true</CanAssignFormula>
      <Formula>if(Left RA, Length 10, 0" - Length 10)</Formula>
    </ParameterInfo>
    <ParameterInfo Name="Length 35" Id="84353">
      <Type>Length</Type>
      <Storage>Double</Storage>
      <Unit>Decimal inches</Unit>
      <Instance>true</Instance>
      <FormulaDetermined>true</FormulaDetermined>
      <CanAssignFormula>true</CanAssignFormula>
      <Formula>if(Left RA, Length 11, 0" - Length 11)</Formula>
    </ParameterInfo>
    <ParameterInfo Name="Length 36" Id="84477">
      <Type>Length</Type>
      <Storage>Double</Storage>
      <Unit>Decimal inches</Unit>
      <Instance>true</Instance>
      <FormulaDetermined>true</FormulaDetermined>
      <CanAssignFormula>true</CanAssignFormula>
      <Formula>if(Left RA, 50" + Width / 2, 50" - Width / 2 - 2.3")</Formula>
    </ParameterInfo>
    <ParameterInfo Name="Length 37" Id="84527">
      <Type>Length</Type>
      <Storage>Double</Storage>
      <Unit>Decimal inches</Unit>
      <Instance>true</Instance>
      <FormulaDetermined>true</FormulaDetermined>
      <CanAssignFormula>true</CanAssignFormula>
      <Formula>if(Left RA, 50" - Width / 2 - 1", 50" + Width / 2)</Formula>
    </ParameterInfo>
    <ParameterInfo Name="Length 38" Id="84329">
      <Type>Length</Type>
      <Storage>Double</Storage>
      <Unit>Decimal inches</Unit>
      <Instance>true</Instance>
      <FormulaDetermined>true</FormulaDetermined>
      <CanAssignFormula>true</CanAssignFormula>
      <Formula>if(Straight Through, Width / 2, 1")</Formula>
    </ParameterInfo>
    <ParameterInfo Name="Length 4" Id="84013">
      <Type>Length</Type>
      <Storage>Double</Storage>
      <Unit>Decimal inches</Unit>
      <FormulaDetermined>true</FormulaDetermined>
      <CanAssignFormula>true</CanAssignFormula>
      <Formula>0" - Length 3</Formula>
    </ParameterInfo>
    <ParameterInfo Name="Length 5" Id="84476">
      <Type>Length</Type>
      <Storage>Double</Storage>
      <Unit>Decimal inches</Unit>
      <CanAssignFormula>true</CanAssignFormula>
      <Formula>RA Filter Width + 4"</Formula>
    </ParameterInfo>
    <ParameterInfo Name="Length 6" Id="84018">
      <Type>Length</Type>
      <Storage>Double</Storage>
      <Unit>Decimal inches</Unit>
      <Instance>true</Instance>
      <FormulaDetermined>true</FormulaDetermined>
      <CanAssignFormula>true</CanAssignFormula>
      <Formula>if(Left RA, Length 10, Length 3)</Formula>
    </ParameterInfo>
    <ParameterInfo Name="Length 7" Id="84019">
      <Type>Length</Type>
      <Storage>Double</Storage>
      <Unit>Decimal inches</Unit>
      <Instance>true</Instance>
      <FormulaDetermined>true</FormulaDetermined>
      <CanAssignFormula>true</CanAssignFormula>
      <Formula>if(Left RA, Length 11, 0" - (Length 11))</Formula>
    </ParameterInfo>
    <ParameterInfo Name="Length 8" Id="84020">
      <Type>Length</Type>
      <Storage>Double</Storage>
      <Unit>Decimal inches</Unit>
      <CanAssignFormula>true</CanAssignFormula>
    </ParameterInfo>
    <ParameterInfo Name="Length 9" Id="84030">
      <Type>Length</Type>
      <Storage>Double</Storage>
      <Unit>Decimal inches</Unit>
      <FormulaDetermined>true</FormulaDetermined>
      <CanAssignFormula>true</CanAssignFormula>
      <Formula>1" + ((Height - 1") - RA Filter Height) / 2</Formula>
    </ParameterInfo>
    <ParameterInfo Name="Load Classification" Id="84062">
      <Group>PG_AELECTRICAL</Group>
      <Type>LoadClassification</Type>
      <Storage>ElementId</Storage>
      <Instance>true</Instance>
    </ParameterInfo>
    <ParameterInfo Name="Manufacturer" Id="-1010108">
      <BuiltinID>ALL_MODEL_MANUFACTURER</BuiltinID>
      <Group>PG_IDENTITY_DATA</Group>
      <Type>Text</Type>
      <Storage>String</Storage>
      <CanAssignFormula>true</CanAssignFormula>
    </ParameterInfo>
    <ParameterInfo Name="Model" Id="-1010109">
      <BuiltinID>ALL_MODEL_MODEL</BuiltinID>
      <Group>PG_IDENTITY_DATA</Group>
      <Type>Text</Type>
      <Storage>String</Storage>
      <CanAssignFormula>true</CanAssignFormula>
    </ParameterInfo>
    <ParameterInfo Name="Nominal Capacity" Id="84064">
      <Group>PG_ENERGY_ANALYSIS</Group>
      <Type>HVACCoolingLoad</Type>
      <Storage>Double</Storage>
      <Unit>BTU (British Thermal Units) per hour</Unit>
      <CanAssignFormula>true</CanAssignFormula>
    </ParameterInfo>
    <ParameterInfo Name="Number of Poles" Id="84061">
      <Group>PG_AELECTRICAL</Group>
      <Type>NumberOfPoles</Type>
      <Storage>Integer</Storage>
      <Instance>true</Instance>
      <CanAssignFormula>true</CanAssignFormula>
    </ParameterInfo>
    <ParameterInfo Name="Offset" Id="83908">
      <Type>Length</Type>
      <Storage>Double</Storage>
      <Unit>Decimal inches</Unit>
      <Instance>true</Instance>
      <FormulaDetermined>true</FormulaDetermined>
      <CanAssignFormula>true</CanAssignFormula>
      <Formula>if(Base Rail Visibility, Base Height, 0")</Formula>
    </ParameterInfo>
    <ParameterInfo Name="OmniClass Number" Id="-1002502">
      <BuiltinID>OMNICLASS_CODE</BuiltinID>
      <Group>PG_IDENTITY_DATA</Group>
      <Type>Text</Type>
      <Storage>String</Storage>
    </ParameterInfo>
    <ParameterInfo Name="OmniClass Title" Id="-1002503">
      <BuiltinID>OMNICLASS_DESCRIPTION</BuiltinID>
      <Group>PG_IDENTITY_DATA</Group>
      <Type>Text</Type>
      <Storage>String</Storage>
      <ReadOnly>true</ReadOnly>
    </ParameterInfo>
    <ParameterInfo Name="Part Type" Id="-1114206">
      <BuiltinID>FAMILY_CONTENT_PART_TYPE</BuiltinID>
      <Group>PG_MECHANICAL</Group>
      <Storage>Integer</Storage>
    </ParameterInfo>
    <ParameterInfo Name="Power Factor" Id="84060">
      <Group>PG_AELECTRICAL</Group>
      <Type>Number</Type>
      <Storage>Double</Storage>
      <Unit>General</Unit>
      <Instance>true</Instance>
      <CanAssignFormula>true</CanAssignFormula>
    </ParameterInfo>
    <ParameterInfo Name="RA Filter Height" Id="84015">
      <Type>Length</Type>
      <Storage>Double</Storage>
      <Unit>Decimal inches</Unit>
      <CanAssignFormula>true</CanAssignFormula>
    </ParameterInfo>
    <ParameterInfo Name="RA Filter Width" Id="84014">
      <Type>Length</Type>
      <Storage>Double</Storage>
      <Unit>Decimal inches</Unit>
      <CanAssignFormula>true</CanAssignFormula>
    </ParameterInfo>
    <ParameterInfo Name="RA Height" Id="84017">
      <Type>HVACDuctSize</Type>
      <Storage>Double</Storage>
      <Unit>Fractional inches</Unit>
      <CanAssignFormula>true</CanAssignFormula>
    </ParameterInfo>
    <ParameterInfo Name="RA Width" Id="84016">
      <Type>HVACDuctSize</Type>
      <Storage>Double</Storage>
      <Unit>Fractional inches</Unit>
      <CanAssignFormula>true</CanAssignFormula>
    </ParameterInfo>
    <ParameterInfo Name="RA Y Offset ST" Id="84706">
      <Type>Length</Type>
      <Storage>Double</Storage>
      <Unit>Decimal inches</Unit>
      <CanAssignFormula>true</CanAssignFormula>
    </ParameterInfo>
    <ParameterInfo Name="Rail Thickness" Id="84728">
      <Type>Length</Type>
      <Storage>Double</Storage>
      <Unit>Decimal inches</Unit>
      <FormulaDetermined>true</FormulaDetermined>
      <CanAssignFormula>true</CanAssignFormula>
      <Formula>0.375"</Formula>
    </ParameterInfo>
    <ParameterInfo Name="Return Air Flow" Id="84070">
      <Group>PG_MECHANICAL</Group>
      <Type>HVACAirflow</Type>
      <Storage>Double</Storage>
      <Unit>Cubic feet per minute</Unit>
      <Instance>true</Instance>
      <CanAssignFormula>true</CanAssignFormula>
    </ParameterInfo>
    <ParameterInfo Name="Right RA" Id="83992">
      <Type>YesNo</Type>
      <Storage>Integer</Storage>
      <Instance>true</Instance>
      <FormulaDetermined>true</FormulaDetermined>
      <CanAssignFormula>true</CanAssignFormula>
      <Formula>not(Left RA)</Formula>
    </ParameterInfo>
    <ParameterInfo Name="Room Calculation Point" Id="-1114399">
      <BuiltinID>ROOM_CALCULATION_POINT</BuiltinID>
      <Type>YesNo</Type>
      <Storage>Integer</Storage>
    </ParameterInfo>
    <ParameterInfo Name="Round Connector Dimension" Id="-1152375">
      <BuiltinID>FAMILY_ROUNDCONNECTOR_DIMENSIONTYPE</BuiltinID>
      <Group>PG_GEOMETRY</Group>
      <Storage>Integer</Storage>
    </ParameterInfo>
    <ParameterInfo Name="SA Height" Id="83994">
      <Type>HVACDuctSize</Type>
      <Storage>Double</Storage>
      <Unit>Fractional inches</Unit>
      <CanAssignFormula>true</CanAssignFormula>
    </ParameterInfo>
    <ParameterInfo Name="SA Width" Id="83993">
      <Type>HVACDuctSize</Type>
      <Storage>Double</Storage>
      <Unit>Fractional inches</Unit>
      <CanAssignFormula>true</CanAssignFormula>
    </ParameterInfo>
    <ParameterInfo Name="SA X Offset EB" Id="83995">
      <Type>Length</Type>
      <Storage>Double</Storage>
      <Unit>Decimal inches</Unit>
      <CanAssignFormula>true</CanAssignFormula>
    </ParameterInfo>
    <ParameterInfo Name="SA X Offset Label" Id="84319">
      <Type>Length</Type>
      <Storage>Double</Storage>
      <Unit>Decimal inches</Unit>
      <Instance>true</Instance>
      <FormulaDetermined>true</FormulaDetermined>
      <CanAssignFormula>true</CanAssignFormula>
      <Formula>if(and(End Blow, Left RA), Width - (SA X Offset EB + SA Width / 2), if(and(End Blow, Right RA), SA X Offset EB + SA Width / 2, Width / 2))</Formula>
    </ParameterInfo>
    <ParameterInfo Name="SA Y Offset Label" Id="83998">
      <Type>Length</Type>
      <Storage>Double</Storage>
      <Unit>Decimal inches</Unit>
      <Instance>true</Instance>
      <FormulaDetermined>true</FormulaDetermined>
      <CanAssignFormula>true</CanAssignFormula>
      <Formula>if(End Blow, 1", SA Y Offset ST + SA Width / 2)</Formula>
    </ParameterInfo>
    <ParameterInfo Name="SA Y Offset ST" Id="84246">
      <Type>Length</Type>
      <Storage>Double</Storage>
      <Unit>Decimal inches</Unit>
      <CanAssignFormula>true</CanAssignFormula>
    </ParameterInfo>
    <ParameterInfo Name="SA Z Offset Label" Id="84332">
      <Type>Length</Type>
      <Storage>Double</Storage>
      <Unit>Decimal inches</Unit>
      <Instance>true</Instance>
      <FormulaDetermined>true</FormulaDetermined>
      <CanAssignFormula>true</CanAssignFormula>
      <Formula>if(and(End Blow, Left RA), SA Z Offset STRH + SA Height / 2, if(and(End Blow, Right RA), SA Z Offset STLH + SA Height / 2, if(and(Straight Through, Left RA), SA Z Offset STLH + SA Height / 2, SA Z Offset STRH + SA Height / 2)))</Formula>
    </ParameterInfo>
    <ParameterInfo Name="SA Z Offset STLH" Id="84248">
      <Type>Length</Type>
      <Storage>Double</Storage>
      <Unit>Decimal inches</Unit>
      <CanAssignFormula>true</CanAssignFormula>
    </ParameterInfo>
    <ParameterInfo Name="SA Z Offset STRH" Id="84247">
      <Type>Length</Type>
      <Storage>Double</Storage>
      <Unit>Decimal inches</Unit>
      <CanAssignFormula>true</CanAssignFormula>
    </ParameterInfo>
    <ParameterInfo Name="SEER" Id="84184">
      <Group>PG_IDENTITY_DATA</Group>
      <Type>Number</Type>
      <Storage>Double</Storage>
      <Unit>General</Unit>
      <CanAssignFormula>true</CanAssignFormula>
    </ParameterInfo>
    <ParameterInfo Name="Shared" Id="-1012834">
      <BuiltinID>FAMILY_SHARED</BuiltinID>
      <Type>YesNo</Type>
      <Storage>Integer</Storage>
    </ParameterInfo>
    <ParameterInfo Name="Straight Through" Id="84245">
      <Type>YesNo</Type>
      <Storage>Integer</Storage>
      <Instance>true</Instance>
      <FormulaDetermined>true</FormulaDetermined>
      <CanAssignFormula>true</CanAssignFormula>
      <Formula>not(End Blow)</Formula>
    </ParameterInfo>
    <ParameterInfo Name="Supply Air Nominal Capacity" Id="84069">
      <Group>PG_MECHANICAL</Group>
      <Type>HVACAirflow</Type>
      <Storage>Double</Storage>
      <Unit>Cubic feet per minute</Unit>
      <Instance>true</Instance>
      <CanAssignFormula>true</CanAssignFormula>
    </ParameterInfo>
    <ParameterInfo Name="Tonnage" Id="84616">
      <Type>Number</Type>
      <Storage>Double</Storage>
      <Unit>General</Unit>
      <CanAssignFormula>true</CanAssignFormula>
    </ParameterInfo>
    <ParameterInfo Name="Type Comments" Id="-1010105">
      <BuiltinID>ALL_MODEL_TYPE_COMMENTS</BuiltinID>
      <Group>PG_IDENTITY_DATA</Group>
      <Type>Text</Type>
      <Storage>String</Storage>
      <CanAssignFormula>true</CanAssignFormula>
    </ParameterInfo>
    <ParameterInfo Name="Type Image" Id="-1152384">
      <BuiltinID>ALL_MODEL_TYPE_IMAGE</BuiltinID>
      <Group>PG_IDENTITY_DATA</Group>
      <Type>Image</Type>
      <Storage>ElementId</Storage>
    </ParameterInfo>
    <ParameterInfo Name="URL" Id="-1010104">
      <BuiltinID>ALL_MODEL_URL</BuiltinID>
      <Group>PG_IDENTITY_DATA</Group>
      <Type>URL</Type>
      <Storage>String</Storage>
    </ParameterInfo>
    <ParameterInfo Name="Voltage" Id="84059">
      <Group>PG_AELECTRICAL</Group>
      <Type>ElectricalPotential</Type>
      <Storage>Double</Storage>
      <Unit>Volts</Unit>
      <Instance>true</Instance>
      <CanAssignFormula>true</CanAssignFormula>
    </ParameterInfo>
    <ParameterInfo Name="Water Diameter" Id="83972">
      <Type>PipeSize</Type>
      <Storage>Double</Storage>
      <Unit>Fractional inches</Unit>
      <CanAssignFormula>true</CanAssignFormula>
      <Formula>Water Radius * 2</Formula>
    </ParameterInfo>
    <ParameterInfo Name="Water Hole Radius" Id="83989">
      <Type>Length</Type>
      <Storage>Double</Storage>
      <Unit>Decimal inches</Unit>
      <CanAssignFormula>true</CanAssignFormula>
      <Formula>Water Radius + 0.197"</Formula>
    </ParameterInfo>
    <ParameterInfo Name="Water In Offset" Id="83978">
      <Type>Length</Type>
      <Storage>Double</Storage>
      <Unit>Decimal inches</Unit>
      <CanAssignFormula>true</CanAssignFormula>
    </ParameterInfo>
    <ParameterInfo Name="Water Out Offset" Id="83977">
      <Type>Length</Type>
      <Storage>Double</Storage>
      <Unit>Decimal inches</Unit>
      <CanAssignFormula>true</CanAssignFormula>
    </ParameterInfo>
    <ParameterInfo Name="Water Radius" Id="83973">
      <Type>PipeSize</Type>
      <Storage>Double</Storage>
      <Unit>Fractional inches</Unit>
      <CanAssignFormula>true</CanAssignFormula>
    </ParameterInfo>
    <ParameterInfo Name="Width" Id="83895">
      <Group>PG_GEOMETRY</Group>
      <Type>Length</Type>
      <Storage>Double</Storage>
      <Unit>Decimal inches</Unit>
      <CanAssignFormula>true</CanAssignFormula>
    </ParameterInfo>
    <ParameterInfo Name="Work Plane-Based" Id="-1012833">
      <BuiltinID>FAMILY_WORK_PLANE_BASED</BuiltinID>
      <Type>YesNo</Type>
      <Storage>Integer</Storage>
    </ParameterInfo>
  </Parameters>
  <Type>Family</Type>
</FamilyInfo>